EduKTM/__init__.py
EduKTM/meta.py
EduKTM/AKT/AKT.py
EduKTM/AKT/AKTNet.py
EduKTM/AKT/__init__.py
EduKTM/DKT/DKT.py
EduKTM/DKT/__init__.py
EduKTM/DKTPlus/DKTPlus.py
EduKTM/DKTPlus/__init__.py
EduKTM/DKTPlus/etl.py
EduKTM/DKVMN/DKVMN.py
EduKTM/DKVMN/__init__.py
EduKTM/EKPT/EKPT.py
EduKTM/EKPT/__init__.py
EduKTM/GKT/GKT.py
EduKTM/GKT/GKTNet.py
EduKTM/GKT/__init__.py
EduKTM/GKT/etl.py
EduKTM/KPT/KPT.py
EduKTM/KPT/__init__.py
EduKTM/LPKT/LPKT.py
EduKTM/LPKT/LPKTNet.py
EduKTM/LPKT/__init__.py
EduKTM/utils/__init__.py
EduKTM/utils/loss.py
EduKTM/utils/tests.py
EduKTM/utils/utils.py
EduKTM/utils/torch/__init__.py
EduKTM/utils/torch/functional.py
EduKTM/utils/torch/rnn.py
EduKTM/utils/torch/extlib/__init__.py
EduKTM/utils/torch/extlib/data.py
EduKTM/utils/torch/extlib/sampler.py
tests/__init__.py
tests/akt/__init__.py
tests/akt/conftest.py
tests/akt/test_akt.py
tests/dkt/__init__.py
tests/dkt/conftest.py
tests/dkt/dkt_test.py
tests/dkt+/__init__.py
tests/dkt+/conftest.py
tests/dkt+/test_dkt_plus.py
tests/dkvmn/__init__.py
tests/dkvmn/conftest.py
tests/dkvmn/test_dkvmn.py
tests/ekpt/__init__.py
tests/ekpt/conftest.py
tests/ekpt/test_ekpt.py
tests/kpt/__init__.py
tests/kpt/conftest.py
tests/kpt/test_kpt.py
tests/lpkt/__init__.py
tests/lpkt/conftest.py
tests/lpkt/test_lpkt.py
EduKTM-0.0.10.dist-info/AUTHORS.md
EduKTM-0.0.10.dist-info/LICENSE
EduKTM-0.0.10.dist-info/METADATA
EduKTM-0.0.10.dist-info/WHEEL
EduKTM-0.0.10.dist-info/top_level.txt
EduKTM-0.0.10.dist-info/RECORD
